{
  "success": "true",
  "result": {
    "resource_id": "-"
  },
  "records": [
    {
      "curr_load": "3086.0",
      "curr_util_rate": "73"
    },
    {
      "fore_maxi_sply_capacity": "4346.3",
      "fore_peak_dema_load": "3550.0",
      "fore_peak_resv_capacity": "796.3",
      "fore_peak_resv_rate": "22.43",
      "fore_peak_resv_indicator": "G",
      "fore_peak_hour_range": "13:00-16:00",
      "publish_time": "113.08.10(六)10:10"
    },
    {
      "yday_date": "113.08.09",
      "yday_maxi_sply_capacity": "4426.3",
      "yday_peak_dema_load": "3848.6",
      "yday_peak_resv_capacity": "577.6",
      "yday_peak_resv_rate": "15.01",
      "yday_peak_resv_indicator": "G"
    },
    {
      "real_hr_maxi_sply_capacity": "4213.2",
      "real_hr_peak_time": "2024.08.10 03:35"
    }
  ]
}
